Workbook

Sheet Line Items
A1: S.No | B1: Item Code | C1: Description | D1: HSN | E1: Qty | F1: UOM | G1: Rate | H1: Amount (taxable) | I1: SGST % | J1: SGST Value | K1: CGST % | L1: CGST Value | M1: Line Total | N1: Gross (Rate x Qty) | O1: Check Amount (Gross x 85% / 1.18) | P1: Diff | Q1: Page | R1: Verification | S1: Cost per unit (excl. GST)
A2: 1 | B2: 50610K0ND00 | C2: BAR COMPSTEP | D2: 87141090 | E2: 1 | F2: PCS | G2: 349 | H2: 251.4 | I2: 0.09 | J2: =ROUND(H2*I2,2) -> 22.63 | K2: 0.09 | L2: =ROUND(H2*K2,2) -> 22.63 | M2: =H2+J2+L2 -> 296.66 | N2: =G2*E2 -> 349 | O2: =ROUND(N2*0.85/1.18,2) -> 251.4 | P2: =ROUND(O2-H2,2) -> 0 | Q2: 1 | R2: Confirmed vs image | S2: =ROUND(H2/E2,2) -> 251.4
A3: 2 | B3: 50610KTED00 | C3: BAR COMPSTEP | D3: 87141090 | E3: 1 | F3: PCS | G3: 266 | H3: 191.61 | I3: 0.09 | J3: =ROUND(H3*I3,2) -> 17.24 | K3: 0.09 | L3: =ROUND(H3*K3,2) -> 17.24 | M3: =H3+J3+L3 -> 226.09 | N3: =G3*E3 -> 266 | O3: =ROUND(N3*0.85/1.18,2) -> 191.61 | P3: =ROUND(O3-H3,2) -> 0 | Q3: 1 | R3: Confirmed vs image | S3: =ROUND(H3/E3,2) -> 191.61
A4: 3 | B4: 50610KTED20 | C4: BAR COMPSTEP | D4: 87141090 | E4: 1 | F4: PCS | G4: 270 | H4: 194.49 | I4: 0.09 | J4: =ROUND(H4*I4,2) -> 17.5 | K4: 0.09 | L4: =ROUND(H4*K4,2) -> 17.5 | M4: =H4+J4+L4 -> 229.49 | N4: =G4*E4 -> 270 | O4: =ROUND(N4*0.85/1.18,2) -> 194.49 | P4: =ROUND(O4-H4,2) -> 0 | Q4: 1 | R4: Confirmed vs image | S4: =ROUND(H4/E4,2) -> 194.49
A5: 4 | B5: 50610K0ND20 | C5: BAR COMPSTEP- | D5: 87141090 | E5: 1 | F5: PCS | G5: 475 | H5: 342.16 | I5: 0.09 | J5: =ROUND(H5*I5,2) -> 30.79 | K5: 0.09 | L5: =ROUND(H5*K5,2) -> 30.79 | M5: =H5+J5+L5 -> 403.74 | N5: =G5*E5 -> 475 | O5: =ROUND(N5*0.85/1.18,2) -> 342.16 | P5: =ROUND(O5-H5,2) -> 0 | Q5: 1 | R5: Confirmed vs image | S5: =ROUND(H5/E5,2) -> 342.16
A6: 5 | B6: 33703K0VB01 | C6: COMPTAIL LIGHT. | D6: 87141090 | E6: 2 | F6: PCS | G6: 292 | H6: 420.68 | I6: 0.09 | J6: =ROUND(H6*I6,2) -> 37.86 | K6: 0.09 | L6: =ROUND(H6*K6,2) -> 37.86 | M6: =H6+J6+L6 -> 496.4 | N6: =G6*E6 -> 584 | O6: =ROUND(N6*0.85/1.18,2) -> 420.68 | P6: =ROUND(O6-H6,2) -> 0 | Q6: 1 | R6: Confirmed vs image | S6: =ROUND(H6/E6,2) -> 210.34
A7: 6 | B7: 33120K0VB01 | C7: HEAD LIGHT UNIT SHINE BS6 | D7: 85122010 | E7: 2 | F7: PCS | G7: 663 | H7: 955.17 | I7: 0.09 | J7: =ROUND(H7*I7,2) -> 85.97 | K7: 0.09 | L7: =ROUND(H7*K7,2) -> 85.97 | M7: =H7+J7+L7 -> 1127.11 | N7: =G7*E7 -> 1326 | O7: =ROUND(N7*0.85/1.18,2) -> 955.17 | P7: =ROUND(O7-H7,2) -> 0 | Q7: 1 | R7: Confirmed vs image | S7: =ROUND(H7/E7,2) -> 477.59
A8: 7 | B8: 37100KTE601 | C8: METER ASSY CB SHINE | D8: 87141090 | E8: 1 | F8: PCS | G8: 1498 | H8: 1079.07 | I8: 0.09 | J8: =ROUND(H8*I8,2) -> 97.12 | K8: 0.09 | L8: =ROUND(H8*K8,2) -> 97.12 | M8: =H8+J8+L8 -> 1273.31 | N8: =G8*E8 -> 1498 | O8: =ROUND(N8*0.85/1.18,2) -> 1079.07 | P8: =ROUND(O8-H8,2) -> 0 | Q8: 1 | R8: Confirmed vs image | S8: =ROUND(H8/E8,2) -> 1079.07
A9: 8 | B9: 37100KTE651 | C9: METER ASSY SHINE DX | D9: 87141090 | E9: 1 | F9: PCS | G9: 1584 | H9: 1141.02 | I9: 0.09 | J9: =ROUND(H9*I9,2) -> 102.69 | K9: 0.09 | L9: =ROUND(H9*K9,2) -> 102.69 | M9: =H9+J9+L9 -> 1346.4 | N9: =G9*E9 -> 1584 | O9: =ROUND(N9*0.85/1.18,2) -> 1141.02 | P9: =ROUND(O9-H9,2) -> 0 | Q9: 1 | R9: Confirmed vs image | S9: =ROUND(H9/E9,2) -> 1141.02
A10: 9 | B10: 37100KTE911 | C10: METER ASSY SHINE O/M | D10: 87141090 | E10: 1 | F10: PCS | G10: 1559 | H10: 1123.01 | I10: 0.09 | J10: =ROUND(H10*I10,2) -> 101.07 | K10: 0.09 | L10: =ROUND(H10*K10,2) -> 101.07 | M10: =H10+J10+L10 -> 1325.15 | N10: =G10*E10 -> 1559 | O10: =ROUND(N10*0.85/1.18,2) -> 1123.01 | P10: =ROUND(O10-H10,2) -> 0 | Q10: 1 | R10: Confirmed vs image | S10: =ROUND(H10/E10,2) -> 1123.01
A11: 10 | B11: 52400KTE651 | C11: RR CUSHION | D11: 87141090 | E11: 2 | F11: PCS | G11: 1171 | H11: 1687.03 | I11: 0.09 | J11: =ROUND(H11*I11,2) -> 151.83 | K11: 0.09 | L11: =ROUND(H11*K11,2) -> 151.83 | M11: =H11+J11+L11 -> 1990.69 | N11: =G11*E11 -> 2342 | O11: =ROUND(N11*0.85/1.18,2) -> 1687.03 | P11: =ROUND(O11-H11,2) -> 0 | Q11: 1 | R11: Confirmed vs image | S11: =ROUND(H11/E11,2) -> 843.52
A12: 11 | B12: 37100KTED81 | C12: SPEEDOMETER ASSY | D12: 87141090 | E12: 1 | F12: PCS | G12: 1052 | H12: 757.8 | I12: 0.09 | J12: =ROUND(H12*I12,2) -> 68.2 | K12: 0.09 | L12: =ROUND(H12*K12,2) -> 68.2 | M12: =H12+J12+L12 -> 894.2 | N12: =G12*E12 -> 1052 | O12: =ROUND(N12*0.85/1.18,2) -> 757.8 | P12: =ROUND(O12-H12,2) -> 0 | Q12: 1 | R12: Confirmed vs image | S12: =ROUND(H12/E12,2) -> 757.8
A13: 12 | B13: 52200KTE650 | C13: SUSPENSION SHINE DX | D13: 87141090 | E13: 1 | F13: PCS | G13: 1548 | H13: 1115.08 | I13: 0.09 | J13: =ROUND(H13*I13,2) -> 100.36 | K13: 0.09 | L13: =ROUND(H13*K13,2) -> 100.36 | M13: =H13+J13+L13 -> 1315.8 | N13: =G13*E13 -> 1548 | O13: =ROUND(N13*0.85/1.18,2) -> 1115.08 | P13: =ROUND(O13-H13,2) -> 0 | Q13: 1 | R13: Confirmed vs image | S13: =ROUND(H13/E13,2) -> 1115.08
... A143: 142 | B143: 33110KTE911 | C143: UNIT HEAD LIGHT | D143: 85122010 | E143: 2 | F143: PCS | G143: 729 | H143: 1050.25 | I143: 0.09 | J143: =ROUND(H143*I143,2) -> 94.52 | K143: 0.09 | L143: =ROUND(H143*K143,2) -> 94.52 | M143: =H143+J143+L143 -> 1239.29 | N143: =G143*E143 -> 1458 | O143: =ROUND(N143*0.85/1.18,2) -> 1050.25 | P143: =ROUND(O143-H143,2) -> 0 | Q143: 5 | R143: Confirmed vs image | S143: =ROUND(H143/E143,2) -> 525.13
A144: TOTAL | C144: 142 line items | E144: =SUM(E2:E143) -> 602 | H144: =SUM(H2:H143) -> 97106.02 | J144: =SUM(J2:J143) -> 8739.57 | L144: =SUM(L2:L143) -> 8739.57 | M144: =SUM(M2:M143) -> 114585.16 | N144: =SUM(N2:N143) -> 134806 | O144: =SUM(O2:O143) -> 97106.02 | P144: =SUM(P2:P143) -> 0 | S144: —
A146: PRICING RULE, verified on all 142 lines: Amount = ROUND(Rate x Qty x 0.85 / 1.18, 2). A flat 15% trade discount, and the Amount column is the GST-exclusive taxable value. Column O recomputes it and column P is the difference - 0.00 on every row.
A147: VERIFICATION STATUS: the Verification column says whether each row was confirmed field-by-field against a high-resolution image, or only read from a 400 DPI render of the scan. Page 1 is confirmed - all 32 rows were correct, no corrections needed. Rows still marked '400 DPI read only' are shaded amber; treat their Item Code, Description and HSN as provisional.
A148: STRUCTURAL WARNING for anyone re-reading the scan: on PAGE 2 the 'TOTAL B/F' text sits on the same line as the first item's code, so the HSN/Qty/Rate/Amount block is printed ONE LINE LOWER than the S.No, code and description. Pages 3, 4 and 5 do not have this offset. Reading page 2 the naive way puts every item from S.No 33 onward on the previous item's figures.
A149: CORRECTIONS FROM VERIFICATION. Page 1: none needed, all 32 rows correct. Page 2: none needed, all 31 rows correct, and the one-line offset described above is confirmed. Page 3: S.No 73 item code 45250KCCS41 -> 45250KCC841. Page 4: none needed, all 31 rows correct. Page 5: none needed, all 17 rows correct. All 142 rows are now confirmed field-by-field against high-resolution images; one correction was needed in total.
A150: BILLING DISCREPANCY OF 365.00 - see the Reconciliation sheet. The 142 line items total 134,806.00 gross, but the invoice footer shows a Sub Total of 135,171.00. The printed Discount of 20,220.90 is exactly 15% of 134,806.00 (15% of 135,171.00 would be 20,275.65), so the seller's own discount was calculated on the correct base. Only the Sub Total line carries the extra 365.00, and it flows through to the Grand Total. Query this with Gayatri before paying or posting.
A151: INVENTORY NOTE: use the orange 'Cost per unit' column for stock valuation, NOT the Rate column. Rate is the seller's list price before discount and before the GST split; the cost you actually bear per unit is the line's taxable amount divided by quantity. Posting Rate as cost overstates stock value substantially.
A152: INVENTORY NOTE: use the orange 'Cost per unit' column for stock valuation, NOT the Rate column. Rate is the seller's list price before discount and before the GST split; the cost you actually bear per unit is the line's taxable amount divided by quantity. Posting Rate as cost overstates stock value substantially.

Sheet Reconciliation
A1: Reconciliation against the invoice's own printed figures
A2: TOTAL C/F on each page is the running sum of ROUND(Rate x Qty / 1.18, 2) - the pre-discount taxable value. It validates Rate and Qty together, so a single misread digit shows up immediately.
A4: Page | B4: Rows | C4: C/F printed | D4: C/F calculated | E4: Diff
A5: 1 | B5: 1 - 32 | C5: 24165.26 | D5: =ROUND(SUMPRODUCT(--('Line Items'!$A$2:$A$143<=32),ROUND('Line Items'!$G$2:$G$143*'Line Items'!$E$2:$E$143/1.18,2)),2) -> 24165.25 | E5: =ROUND(D5-C5,2) -> -0.01
A6: 2 | B6: 33 - 63 | C6: 49516.11 | D6: =ROUND(SUMPRODUCT(--('Line Items'!$A$2:$A$143<=63),ROUND('Line Items'!$G$2:$G$143*'Line Items'!$E$2:$E$143/1.18,2)),2) -> 49516.09 | E6: =ROUND(D6-C6,2) -> -0.02
A7: 3 | B7: 64 - 94 | C7: 75811.03 | D7: =ROUND(SUMPRODUCT(--('Line Items'!$A$2:$A$143<=94),ROUND('Line Items'!$G$2:$G$143*'Line Items'!$E$2:$E$143/1.18,2)),2) -> 75811.01 | E7: =ROUND(D7-C7,2) -> -0.02
A8: 4 | B8: 95 - 125 | C8: 95974.56 | D8: =ROUND(SUMPRODUCT(--('Line Items'!$A$2:$A$143<=125),ROUND('Line Items'!$G$2:$G$143*'Line Items'!$E$2:$E$143/1.18,2)),2) -> 95974.53 | E8: =ROUND(D8-C8,2) -> -0.03
A9: 5 | B9: 126 - 142 | C9: not printed | D9: =ROUND(SUMPRODUCT(ROUND('Line Items'!$G$2:$G$143*'Line Items'!$E$2:$E$143/1.18,2)),2) -> 114242.3
A12: Grand total reconciliation
A13: Item | B13: Printed on invoice | C13: From these 142 lines | D13: Diff
A14: Sub Total (gross) | B14: 135171 | C14: ='Line Items'!N144 -> 134806 | D14: =ROUND(C14-B14,2) -> -365
A15: Discount (15%) | B15: 20220.9 | C15: =ROUND('Line Items'!N144*0.15,2) -> 20220.9 | D15: =ROUND(C15-B15,2) -> 0
A16: Taxable / Net | B16: 97415.28 | C16: ='Line Items'!H144 -> 97106.02 | D16: =ROUND(C16-B16,2) -> -309.26
A17: CGST @ 9% | B17: 8767.41 | C17: ='Line Items'!L144 -> 8739.57 | D17: =ROUND(C17-B17,2) -> -27.84
A18: SGST @ 9% | B18: 8767.41 | C18: ='Line Items'!J144 -> 8739.57 | D18: =ROUND(C18-B18,2) -> -27.84
A19: GRAND TOTAL | B19: 114950 | C19: ='Line Items'!M144 -> 114585.16 | D19: =ROUND(C19-B19,2) -> -364.84
A21: OPEN ITEM - one line is missing
A22: The printed Discount of 20,220.90 is EXACTLY 15% of the 134,806.00 gross of these 142 lines. 15% of the printed Sub Total (135,171.00) would be 20,275.65, which is NOT what the invoice shows. So the seller's system calculated the discount on 134,806.00 - it agrees with the line items.
A23: Only the Sub Total line carries the extra 365.00, and it flows straight through: Sub Total 135,171.00 less Discount 20,220.90 = 114,950.10, billed as 114,950.00. Built from the line items instead: 134,806.00 less 20,220.90 = 114,585.10, i.e. a Grand Total of 114,585.00. The difference is exactly 365.00.
A24: Taxable should be 97,106.02 (CGST and SGST 8,739.54 each) rather than the printed 97,415.28 (8,767.41 each). Input tax credit claimed on this invoice would be overstated by 27.87 in each of CGST and SGST.
A25: All five item pages are now accounted for. Pages 1-4 each reconcile to their printed TOTAL C/F within 0.03, which could not happen if a line were missing from them. Pages 1, 2, 3 and 5 have each been confirmed field-by-field against a high-resolution image and none carries an unnumbered extra line. So the 365.00 is not a line item that was missed in extraction - it is present only in the invoice footer. Raise it with Gayatri Auto Distributors: either a charge was applied without being itemised, or the Sub Total is overstated.

Sheet Invoice Summary
A1: TAX INVOICE - CREDIT
A3: Seller | B3: GAYATRI AUTO DISTRIBUTORS (Honda)
A4: Seller Address | B4: 25-106\10, Ice Factory Road, R.R Nagar, Kabela, Vijayawada - 520012
A5: Seller Phone | B5: 8099550066, 9030909094
A6: Seller Email | B6: GAYATRIHONDA@GMAIL.COM
A7: Seller GSTIN | B7: 37AAWFG4156F1Z0
A8: IRN | B8: 71745dcbb6f0fe54b5432cae0ef9180884465f11bf9013af9915cf8810dd0ad5
A9: Invoice No. | B9: V006026
A10: Invoice Date | B10: 26/02/2026
A11: Type | B11: TAX INVOICE - CREDIT
A12: Buyer | B12: M/s SRI SRI SATYA SAI AUTOMOBILE AGENCY-TPG
A13: Buyer Address | B13: Dr.No.2-12-27/1, OPP: BSNL Telephone Exchange, Railway Station Road, TADEPALLIGUDEM
A14: Buyer Phone | B14: 9014638309
... A23: UPI | B23: gayatrivja@kotak
A25: TOTALS (as printed)
A26: Sub Total | B26: 135171
A27: Discount | B27: 20220.9
A28: Taxable (GST 18%) | B28: 97415.28
A29: CGST Payable | B29: 8767.41
A30: SGST Payable | B30: 8767.41
A31: Total GST | B31: 17534.82
A32: TCS | B32: 0
A33: GRAND TOTAL | B33: 114950
A34: In words | B34: Rs. One Lakh Fourteen Thousand Nine Hundred Fifty Only
A35: Old Balance | B35: 244350
A36: New Balance | B36: 359300
A37: Gross (page 5 footer) | B37: 135171
A38: Net (page 5 footer) | B38: 97415.28

Sheet HSN Summary
A1: Summary by HSN (all lines 18%: CGST 9% + SGST 9%)
A3: HSN | B3: Lines | C3: Qty | D3: Taxable | E3: CGST | F3: SGST | G3: Total
A4: 40169330 | B4: =COUNTIF('Line Items'!$D$2:$D$143,$A4) -> 1 | C4: =SUMIF('Line Items'!$D$2:$D$143,$A4,'Line Items'!$E$2:$E$143) -> 20 | D4: =ROUND(SUMIF('Line Items'!$D$2:$D$143,$A4,'Line Items'!$H$2:$H$143),2) -> 461.02 | E4: =ROUND(D4*9%,2) -> 41.49 | F4: =E4 -> 41.49 | G4: =D4+E4+F4 -> 544
A5: 40169990 | B5: =COUNTIF('Line Items'!$D$2:$D$143,$A5) -> 1 | C5: =SUMIF('Line Items'!$D$2:$D$143,$A5,'Line Items'!$E$2:$E$143) -> 10 | D5: =ROUND(SUMIF('Line Items'!$D$2:$D$143,$A5,'Line Items'!$H$2:$H$143),2) -> 504.24 | E5: =ROUND(D5*9%,2) -> 45.38 | F5: =E5 -> 45.38 | G5: =D5+E5+F5 -> 595
A6: 73151100 | B6: =COUNTIF('Line Items'!$D$2:$D$143,$A6) -> 1 | C6: =SUMIF('Line Items'!$D$2:$D$143,$A6,'Line Items'!$E$2:$E$143) -> 5 | D6: =ROUND(SUMIF('Line Items'!$D$2:$D$143,$A6,'Line Items'!$H$2:$H$143),2) -> 583.47 | E6: =ROUND(D6*9%,2) -> 52.51 | F6: =E6 -> 52.51 | G6: =D6+E6+F6 -> 688.49
A7: 83012000 | B7: =COUNTIF('Line Items'!$D$2:$D$143,$A7) -> 3 | C7: =SUMIF('Line Items'!$D$2:$D$143,$A7,'Line Items'!$E$2:$E$143) -> 4 | D7: =ROUND(SUMIF('Line Items'!$D$2:$D$143,$A7,'Line Items'!$H$2:$H$143),2) -> 2945.46 | E7: =ROUND(D7*9%,2) -> 265.09 | F7: =E7 -> 265.09 | G7: =D7+E7+F7 -> 3475.64
A8: 84099111 | B8: =COUNTIF('Line Items'!$D$2:$D$143,$A8) -> 2 | C8: =SUMIF('Line Items'!$D$2:$D$143,$A8,'Line Items'!$E$2:$E$143) -> 2 | D8: =ROUND(SUMIF('Line Items'!$D$2:$D$143,$A8,'Line Items'!$H$2:$H$143),2) -> 338.56 | E8: =ROUND(D8*9%,2) -> 30.47 | F8: =E8 -> 30.47 | G8: =D8+E8+F8 -> 399.5
A9: 84099191 | B9: =COUNTIF('Line Items'!$D$2:$D$143,$A9) -> 1 | C9: =SUMIF('Line Items'!$D$2:$D$143,$A9,'Line Items'!$E$2:$E$143) -> 1 | D9: =ROUND(SUMIF('Line Items'!$D$2:$D$143,$A9,'Line Items'!$H$2:$H$143),2) -> 528.01 | E9: =ROUND(D9*9%,2) -> 47.52 | F9: =E9 -> 47.52 | G9: =D9+E9+F9 -> 623.05
A10: 84099990 | B10: =COUNTIF('Line Items'!$D$2:$D$143,$A10) -> 1 | C10: =SUMIF('Line Items'!$D$2:$D$143,$A10,'Line Items'!$E$2:$E$143) -> 5 | D10: =ROUND(SUMIF('Line Items'!$D$2:$D$143,$A10,'Line Items'!$H$2:$H$143),2) -> 1213.77 | E10: =ROUND(D10*9%,2) -> 109.24 | F10: =E10 -> 109.24 | G10: =D10+E10+F10 -> 1432.25
A11: 84212300 | B11: =COUNTIF('Line Items'!$D$2:$D$143,$A11) -> 1 | C11: =SUMIF('Line Items'!$D$2:$D$143,$A11,'Line Items'!$E$2:$E$143) -> 10 | D11: =ROUND(SUMIF('Line Items'!$D$2:$D$143,$A11,'Line Items'!$H$2:$H$143),2) -> 655.51 | E11: =ROUND(D11*9%,2) -> 59 | F11: =E11 -> 59 | G11: =D11+E11+F11 -> 773.51
A12: 84213990 | B12: =COUNTIF('Line Items'!$D$2:$D$143,$A12) -> 2 | C12: =SUMIF('Line Items'!$D$2:$D$143,$A12,'Line Items'!$E$2:$E$143) -> 4 | D12: =ROUND(SUMIF('Line Items'!$D$2:$D$143,$A12,'Line Items'!$H$2:$H$143),2) -> 291.01 | E12: =ROUND(D12*9%,2) -> 26.19 | F12: =E12 -> 26.19 | G12: =D12+E12+F12 -> 343.39
A13: 84219900 | B13: =COUNTIF('Line Items'!$D$2:$D$143,$A13) -> 2 | C13: =SUMIF('Line Items'!$D$2:$D$143,$A13,'Line Items'!$E$2:$E$143) -> 10 | D13: =ROUND(SUMIF('Line Items'!$D$2:$D$143,$A13,'Line Items'!$H$2:$H$143),2) -> 1156.14 | E13: =ROUND(D13*9%,2) -> 104.05 | F13: =E13 -> 104.05 | G13: =D13+E13+F13 -> 1364.24
A14: 84841090 | B14: =COUNTIF('Line Items'!$D$2:$D$143,$A14) -> 1 | C14: =SUMIF('Line Items'!$D$2:$D$143,$A14,'Line Items'!$E$2:$E$143) -> 10 | D14: =ROUND(SUMIF('Line Items'!$D$2:$D$143,$A14,'Line Items'!$H$2:$H$143),2) -> 669.92 | E14: =ROUND(D14*9%,2) -> 60.29 | F14: =E14 -> 60.29 | G14: =D14+E14+F14 -> 790.5
A15: 85114000 | B15: =COUNTIF('Line Items'!$D$2:$D$143,$A15) -> 3 | C15: =SUMIF('Line Items'!$D$2:$D$143,$A15,'Line Items'!$E$2:$E$143) -> 3 | D15: =ROUND(SUMIF('Line Items'!$D$2:$D$143,$A15,'Line Items'!$H$2:$H$143),2) -> 2529.11 | E15: =ROUND(D15*9%,2) -> 227.62 | F15: =E15 -> 227.62 | G15: =D15+E15+F15 -> 2984.35
... A26: 90292020 | B26: =COUNTIF('Line Items'!$D$2:$D$143,$A26) -> 1 | C26: =SUMIF('Line Items'!$D$2:$D$143,$A26,'Line Items'!$E$2:$E$143) -> 1 | D26: =ROUND(SUMIF('Line Items'!$D$2:$D$143,$A26,'Line Items'!$H$2:$H$143),2) -> 152.71 | E26: =ROUND(D26*9%,2) -> 13.74 | F26: =E26 -> 13.74 | G26: =D26+E26+F26 -> 180.19
A27: TOTAL | B27: =SUM(B4:B26) -> 142 | C27: =SUM(C4:C26) -> 602 | D27: =SUM(D4:D26) -> 97106.02 | E27: =SUM(E4:E26) -> 8739.53 | F27: =SUM(F4:F26) -> 8739.53 | G27: =SUM(G4:G26) -> 114585.08
