Workbook

Sheet Line Items
A1: Sn | B1: Code | C1: Name | D1: HSN | E1: M.R.P | F1: Qty | G1: Rate | H1: Amount | I1: Dis % | J1: Taxable Value | K1: CGST % | L1: CGST Value | M1: SGST % | N1: SGST Value | O1: Line Total (Taxable+GST) | P1: Effective M.R.P (Amount x 1.18 / Qty) | Q1: Check Taxable (Amount x 80%) | R1: Diff | S1: Check CGST (Taxable x 9%) | T1: Diff | U1: Page | V1: Verification | W1: Note | X1: Cost per unit (excl. GST)
A2: 1 | B2: 35340KCC900S | C2: SWITCH ASSY FR STO | D2: 85365020 | E2: 45 | F2: 10 | G2: 38.14 | H2: 381.36 | I2: 0.2 | J2: 305.08 | K2: 0.09 | L2: 27.46 | M2: 0.09 | N2: 27.46 | O2: =J2+L2+N2 -> 360 | P2: =ROUND(H2*1.18/F2,2) -> 45 | Q2: =ROUND(H2*0.8,2) -> 305.09 | R2: =ROUND(Q2-J2,2) -> 0.01 | S2: =ROUND(J2*9%,2) -> 27.46 | T2: =ROUND(S2-L2,2) -> 0 | U2: 1 | V2: Confirmed vs image | X2: =ROUND(J2/F2,2) -> 30.51
A3: 2 | B3: 35340KTP890S | C3: SW ASSY FR STOP | D3: 85365020 | E3: 40 | F3: 20 | G3: 33.9 | H3: 677.97 | I3: 0.2 | J3: 542.37 | K3: 0.09 | L3: 48.81 | M3: 0.09 | N3: 48.81 | O3: =J3+L3+N3 -> 639.99 | P3: =ROUND(H3*1.18/F3,2) -> 40 | Q3: =ROUND(H3*0.8,2) -> 542.38 | R3: =ROUND(Q3-J3,2) -> 0.01 | S3: =ROUND(J3*9%,2) -> 48.81 | T3: =ROUND(S3-L3,2) -> 0 | U3: 1 | V3: Confirmed vs image | X3: =ROUND(J3/F3,2) -> 27.12
A4: 3 | B4: 35750001000S | C4: NETURAL SWITCH ALL | D4: 85361090 | E4: 50 | F4: 5 | G4: 42.37 | H4: 211.86 | I4: 0.2 | J4: 169.49 | K4: 0.09 | L4: 15.25 | M4: 0.09 | N4: 15.25 | O4: =J4+L4+N4 -> 199.99 | P4: =ROUND(H4*1.18/F4,2) -> 50 | Q4: =ROUND(H4*0.8,2) -> 169.49 | R4: =ROUND(Q4-J4,2) -> 0 | S4: =ROUND(J4*9%,2) -> 15.25 | T4: =ROUND(S4-L4,2) -> 0 | U4: 1 | V4: Confirmed vs image | X4: =ROUND(J4/F4,2) -> 33.9
A5: 4 | B5: 35753035010S | C5: NATURAL BLADE ALL | D5: 87141090 | E5: 14 | F5: 20 | G5: 11.53 | H5: 230.51 | I5: 0.2 | J5: 184.41 | K5: 0.09 | L5: 16.6 | M5: 0.09 | N5: 16.6 | O5: =J5+L5+N5 -> 217.61 | P5: =ROUND(H5*1.18/F5,2) -> 13.6 | Q5: =ROUND(H5*0.8,2) -> 184.41 | R5: =ROUND(Q5-J5,2) -> 0 | S5: =ROUND(J5*9%,2) -> 16.6 | T5: =ROUND(S5-L5,2) -> 0 | U5: 1 | V5: Confirmed vs image | X5: =ROUND(J5/F5,2) -> 9.22
A6: 5 | B6: 35759KTRA01S | C6: CONTACT ASSY CHAN | D6: 85369090 | E6: 50 | F6: 5 | G6: 42.37 | H6: 211.86 | I6: 0.2 | J6: 169.49 | K6: 0.09 | L6: 15.25 | M6: 0.09 | N6: 15.25 | O6: =J6+L6+N6 -> 199.99 | P6: =ROUND(H6*1.18/F6,2) -> 50 | Q6: =ROUND(H6*0.8,2) -> 169.49 | R6: =ROUND(Q6-J6,2) -> 0 | S6: =ROUND(J6*9%,2) -> 15.25 | T6: =ROUND(S6-L6,2) -> 0 | U6: 1 | V6: Confirmed vs image | X6: =ROUND(J6/F6,2) -> 33.9
A7: 6 | B7: 35850KR3870S | C7: GLM SLEF RELAY | D7: 85365020 | E7: 285 | F7: 20 | G7: 241.53 | H7: 4830.51 | I7: 0.2 | J7: 3864.41 | K7: 0.09 | L7: 347.8 | M7: 0.09 | N7: 347.8 | O7: =J7+L7+N7 -> 4560.01 | P7: =ROUND(H7*1.18/F7,2) -> 285 | Q7: =ROUND(H7*0.8,2) -> 3864.41 | R7: =ROUND(Q7-J7,2) -> 0 | S7: =ROUND(J7*9%,2) -> 347.8 | T7: =ROUND(S7-L7,2) -> 0 | U7: 1 | V7: Confirmed vs image | X7: =ROUND(J7/F7,2) -> 193.22
A8: 7 | B8: 37100AAEH00S | C8: METER ASSY | D8: 87141090 | E8: 1175 | F8: 1 | G8: 995.76 | H8: 995.76 | I8: 0.2 | J8: 796.61 | K8: 0.09 | L8: 71.69 | M8: 0.09 | N8: 71.69 | O8: =J8+L8+N8 -> 939.99 | P8: =ROUND(H8*1.18/F8,2) -> 1175 | Q8: =ROUND(H8*0.8,2) -> 796.61 | R8: =ROUND(Q8-J8,2) -> 0 | S8: =ROUND(J8*9%,2) -> 71.69 | T8: =ROUND(S8-L8,2) -> 0 | U8: 1 | V8: Confirmed vs image | X8: =ROUND(J8/F8,2) -> 796.61
A9: 8 | B9: 37211AAC021S | C9: CASE UPPER ASSY A | D9: 87141090 | E9: 314 | F9: 3 | G9: 266.1 | H9: 798.31 | I9: 0.2 | J9: 638.64 | K9: 0.09 | L9: 57.48 | M9: 0.09 | N9: 57.48 | O9: =J9+L9+N9 -> 753.6 | P9: =ROUND(H9*1.18/F9,2) -> 314 | Q9: =ROUND(H9*0.8,2) -> 638.65 | R9: =ROUND(Q9-J9,2) -> 0.01 | S9: =ROUND(J9*9%,2) -> 57.48 | T9: =ROUND(S9-L9,2) -> 0 | U9: 1 | V9: Confirmed vs image | X9: =ROUND(J9/F9,2) -> 212.88
A10: 9 | B10: 37211KTRA21S | C10: GLA DIG SM UPPER | D10: 87141090 | E10: 142 | F10: 5 | G10: 120.34 | H10: 601.69 | I10: 0.2 | J10: 481.36 | K10: 0.09 | L10: 43.32 | M10: 0.09 | N10: 43.32 | O10: =J10+L10+N10 -> 568 | P10: =ROUND(H10*1.18/F10,2) -> 142 | Q10: =ROUND(H10*0.8,2) -> 481.35 | R10: =ROUND(Q10-J10,2) -> -0.01 | S10: =ROUND(J10*9%,2) -> 43.32 | T10: =ROUND(S10-L10,2) -> 0 | U10: 1 | V10: Confirmed vs image | X10: =ROUND(J10/F10,2) -> 96.27
A11: 10 | B11: 37610KST951S | C11: C ASE UPPER ASSY | D11: 87141090 | E11: 131 | F11: 5 | G11: 111.02 | H11: 555.08 | I11: 0.2 | J11: 444.07 | K11: 0.09 | L11: 39.97 | M11: 0.09 | N11: 39.97 | O11: =J11+L11+N11 -> 524.01 | P11: =ROUND(H11*1.18/F11,2) -> 131 | Q11: =ROUND(H11*0.8,2) -> 444.06 | R11: =ROUND(Q11-J11,2) -> -0.01 | S11: =ROUND(J11*9%,2) -> 39.97 | T11: =ROUND(S11-L11,2) -> 0 | U11: 1 | V11: Confirmed vs image | X11: =ROUND(J11/F11,2) -> 88.81
A12: 11 | B12: 37700KTRA21S | C12: SENSOR ASSY SPEED | D12: 90299000 | E12: 715 | F12: 2 | G12: 605.93 | H12: 1211.86 | I12: 0.2 | J12: 969.49 | K12: 0.09 | L12: 87.25 | M12: 0.09 | N12: 87.25 | O12: =J12+L12+N12 -> 1143.99 | P12: =ROUND(H12*1.18/F12,2) -> 715 | Q12: =ROUND(H12*0.8,2) -> 969.49 | R12: =ROUND(Q12-J12,2) -> 0 | S12: =ROUND(J12*9%,2) -> 87.25 | T12: =ROUND(S12-L12,2) -> 0 | U12: 1 | V12: Confirmed vs image | X12: =ROUND(J12/F12,2) -> 484.75
A13: 12 | B13: 37700KWA830S | C13: SP.SENSOR ASSY | D13: 90299000 | E13: 640 | F13: 2 | G13: 542.37 | H13: 1084.75 | I13: 0.2 | J13: 867.8 | K13: 0.09 | L13: 78.1 | M13: 0.09 | N13: 78.1 | O13: =J13+L13+N13 -> 1024 | P13: =ROUND(H13*1.18/F13,2) -> 640 | Q13: =ROUND(H13*0.8,2) -> 867.8 | R13: =ROUND(Q13-J13,2) -> 0 | S13: =ROUND(J13*9%,2) -> 78.1 | T13: =ROUND(S13-L13,2) -> 0 | U13: 1 | V13: Confirmed vs image | X13: =ROUND(J13/F13,2) -> 433.9
... A238: 237 | B238: K96961HF100FR | C238: KIT WHEEL BEARING | D238: 84829900 | E238: 200 | F238: 5 | G238: 169.49 | H238: 847.46 | I238: 0.2 | J238: 677.97 | K238: 0.09 | L238: 61.02 | M238: 0.09 | N238: 61.02 | O238: =J238+L238+N238 -> 800.01 | P238: =ROUND(H238*1.18/F238,2) -> 200 | Q238: =ROUND(H238*0.8,2) -> 677.97 | R238: =ROUND(Q238-J238,2) -> 0 | S238: =ROUND(J238*9%,2) -> 61.02 | T238: =ROUND(S238-L238,2) -> 0 | U238: 8 | V238: Confirmed vs image | X238: =ROUND(J238/F238,2) -> 135.59
A239: TOTAL | C239: 237 line items | F239: =SUM(F2:F238) -> 2530 | H239: =SUM(H2:H238) -> 318542.4 | J239: =SUM(J2:J238) -> 254833.86 | L239: =SUM(L2:L238) -> 22935.05 | N239: =SUM(N2:N238) -> 22935.05 | O239: =SUM(O2:O238) -> 300703.96 | Q239: =SUM(Q2:Q238) -> 254833.88 | S239: =SUM(S2:S238) -> 22935.05 | X239: —
A241: Column P re-derives the true M.R.P from the printed Amount: Amount x 1.18 / Qty. On 12 lines it differs from column E because the invoice displays M.R.P rounded to whole rupees - Sn 4 (13.60 shown as 14), 26 (33.75), 27 (27.50), 35 (73.50), 50 (82.50), 66 (13.50), 125 (15.50), 141 (11.50), 149 (14.40), 159 (23.60), plus 153 and 199 which differ by one paisa. Use column P for any price calculation.
A242: Columns R and T recheck the printed Taxable Value and CGST. Differences are only ever 0.01 and only at a half-paisa boundary, because the seller's software rounds x.xx5 down while Excel rounds it up. Nothing larger than 0.01 appears anywhere in the 237 rows.
A243: VERIFICATION STATUS: the Verification column says whether that row was confirmed field-by-field against a high-resolution image of the invoice page. Pages 1 and 2 are confirmed. Rows on pages 3-8 are shaded amber and NOT yet verified - treat their HSN codes and item names as provisional.
A244: Corrections applied from verification so far. Page 1: none needed, all 34 rows correct. Page 2: Sn 52 HSN 87141090 -> 40169990 and name BOSH BODY PIN -> BOSH BOOT PIN; Sn 53 HSN 40169990 -> 73202000; Sn 54 HSN 73202000 -> 87141090 (the HSN column had slipped down one row across Sn 52-54); Sn 66 code 45541AAF400S -> 45451AAF400S. Page 3: Sn 98 HSN 40169990 -> 40169390. Page 4: Sn 113 code 53140KCT900S -> 53140KFN850S. Page 5 (MAJOR): the numeric block for Sn 156-166 was shifted up one row - each item held the NEXT item's MRP, Qty, Rate, Amount, Taxable and tax. All 11 rows realigned (77 cells). Sn 165 code 90305KST942S -> 90306KST942S and name NUT FLANGE PT -> NUT FLUNGE PT. Sn 166 previously carried a value reconstructed from the page balances; that reconstruction was an artefact of the shift and has been replaced with the printed figures (MRP 155, Qty 3, Amount 394.07). Page 6: Sn 171 code 91001KSP911S -> 91002KSP911S; Sn 181 name OIL SEAL GEAR SHAFT -> CLULIVER O-RING ALL and HSN 40169330 -> 40169320; Sn 184 code 961006001009S -> 961006001000S; Sn 196 HSN 84099191 -> 84099112; Sn 197 name KIT, CYLINDER -> KIT CYLINDER. Page 7: no substantive errors; Sn 205 name corrected to KIT CAM CHAIN*-. Page 8: none needed, all 5 rows correct. ALL 237 ROWS ARE NOW CONFIRMED FIELD-BY-FIELD AGAINST LEGIBLE IMAGES OF ALL EIGHT PAGES. Ten corrections were needed in total. The three cells previously inferred rather than read (Sn 182 MRP/Qty, Sn 215 Qty, Sn 166) are all confirmed or corrected. A re-check at 500 DPI independently reconfirmed Sn 52 as BOSH BOOT PIN and Sn 165 as 90306KST942S.
A245: The invoice lists items in ascending item-code order, which is an independent check on the Code column. All 237 codes now sort correctly except Sn 171 - see its Note.
A246: NOTE ON THE PAGE BALANCES SHEET: a whole-block numeric shift like the one found on page 5 does NOT disturb any page balance, because the same numbers are still present - only their assignment to items changes. Those green ticks were therefore never sufficient on their own. Every page has since been confirmed against a legible image, which is what actually settles it.
A247: INVENTORY NOTE: use the orange 'Cost per unit' column for stock valuation, NOT the Rate column. Rate is the seller's list price before discount and before the GST split; the cost you actually bear per unit is the line's taxable amount divided by quantity. Posting Rate as cost overstates stock value substantially.

Sheet Page Balances
A1: Page 'Closing Balance' reconciliation
A2: Every page of this invoice carries the running total forward. These are the eight checkpoints the extraction was validated against.
A4: Page | B4: Rows (Sn) | C4: Qty printed | D4: Qty calc | E4: Diff | F4: Taxable printed | G4: Taxable calc | H4: Diff | I4: CGST printed | J4: CGST calc | K4: Diff
A5: 1 | B5: 1 - 34 | C5: 381 | D5: =SUMIF('Line Items'!$A$2:$A$238,"<="&34,'Line Items'!$F$2:$F$238) -> 381 | E5: =D5-C5 -> 0 | F5: 30585.76 | G5: =ROUND(SUMIF('Line Items'!$A$2:$A$238,"<="&34,'Line Items'!$J$2:$J$238),2) -> 30585.77 | H5: =ROUND(G5-F5,2) -> 0.01 | I5: 2752.69 | J5: =ROUND(SUMIF('Line Items'!$A$2:$A$238,"<="&34,'Line Items'!$L$2:$L$238),2) -> 2752.69 | K5: =ROUND(J5-I5,2) -> 0
A6: 2 | B6: 1 - 67 | C6: 953 | D6: =SUMIF('Line Items'!$A$2:$A$238,"<="&67,'Line Items'!$F$2:$F$238) -> 953 | E6: =D6-C6 -> 0 | F6: 70366.78 | G6: =ROUND(SUMIF('Line Items'!$A$2:$A$238,"<="&67,'Line Items'!$J$2:$J$238),2) -> 70366.78 | H6: =ROUND(G6-F6,2) -> 0 | I6: 6333 | J6: =ROUND(SUMIF('Line Items'!$A$2:$A$238,"<="&67,'Line Items'!$L$2:$L$238),2) -> 6333 | K6: =ROUND(J6-I6,2) -> 0
A7: 3 | B7: 1 - 100 | C7: 1116 | D7: =SUMIF('Line Items'!$A$2:$A$238,"<="&100,'Line Items'!$F$2:$F$238) -> 1116 | E7: =D7-C7 -> 0 | F7: 105151.19 | G7: =ROUND(SUMIF('Line Items'!$A$2:$A$238,"<="&100,'Line Items'!$J$2:$J$238),2) -> 105151.19 | H7: =ROUND(G7-F7,2) -> 0 | I7: 9463.59 | J7: =ROUND(SUMIF('Line Items'!$A$2:$A$238,"<="&100,'Line Items'!$L$2:$L$238),2) -> 9463.59 | K7: =ROUND(J7-I7,2) -> 0
A8: 4 | B8: 1 - 133 | C8: 1357 | D8: =SUMIF('Line Items'!$A$2:$A$238,"<="&133,'Line Items'!$F$2:$F$238) -> 1357 | E8: =D8-C8 -> 0 | F8: 130004.07 | G8: =ROUND(SUMIF('Line Items'!$A$2:$A$238,"<="&133,'Line Items'!$J$2:$J$238),2) -> 130004.06 | H8: =ROUND(G8-F8,2) -> -0.01 | I8: 11700.37 | J8: =ROUND(SUMIF('Line Items'!$A$2:$A$238,"<="&133,'Line Items'!$L$2:$L$238),2) -> 11700.37 | K8: =ROUND(J8-I8,2) -> 0
A9: 5 | B9: 1 - 166 | C9: 1673 | D9: =SUMIF('Line Items'!$A$2:$A$238,"<="&166,'Line Items'!$F$2:$F$238) -> 1673 | E9: =D9-C9 -> 0 | F9: 145883.39 | G9: =ROUND(SUMIF('Line Items'!$A$2:$A$238,"<="&166,'Line Items'!$J$2:$J$238),2) -> 145883.36 | H9: =ROUND(G9-F9,2) -> -0.03 | I9: 13129.48 | J9: =ROUND(SUMIF('Line Items'!$A$2:$A$238,"<="&166,'Line Items'!$L$2:$L$238),2) -> 13129.48 | K9: =ROUND(J9-I9,2) -> 0
A10: 6 | B10: 1 - 199 | C10: 2189 | D10: =SUMIF('Line Items'!$A$2:$A$238,"<="&199,'Line Items'!$F$2:$F$238) -> 2189 | E10: =D10-C10 -> 0 | F10: 192061.02 | G10: =ROUND(SUMIF('Line Items'!$A$2:$A$238,"<="&199,'Line Items'!$J$2:$J$238),2) -> 192060.98 | H10: =ROUND(G10-F10,2) -> -0.04 | I10: 17285.46 | J10: =ROUND(SUMIF('Line Items'!$A$2:$A$238,"<="&199,'Line Items'!$L$2:$L$238),2) -> 17285.46 | K10: =ROUND(J10-I10,2) -> 0
A11: 7 | B11: 1 - 232 | C11: 2490 | D11: =SUMIF('Line Items'!$A$2:$A$238,"<="&232,'Line Items'!$F$2:$F$238) -> 2490 | E11: =D11-C11 -> 0 | F11: 247993.22 | G11: =ROUND(SUMIF('Line Items'!$A$2:$A$238,"<="&232,'Line Items'!$J$2:$J$238),2) -> 247993.18 | H11: =ROUND(G11-F11,2) -> -0.04 | I11: 22319.38 | J11: =ROUND(SUMIF('Line Items'!$A$2:$A$238,"<="&232,'Line Items'!$L$2:$L$238),2) -> 22319.38 | K11: =ROUND(J11-I11,2) -> 0
A12: 8 (Total) | B12: 1 - 237 | C12: 2530 | D12: =SUMIF('Line Items'!$A$2:$A$238,"<="&237,'Line Items'!$F$2:$F$238) -> 2530 | E12: =D12-C12 -> 0 | F12: 254833.9 | G12: =ROUND(SUMIF('Line Items'!$A$2:$A$238,"<="&237,'Line Items'!$J$2:$J$238),2) -> 254833.86 | H12: =ROUND(G12-F12,2) -> -0.04 | I12: 22935.05 | J12: =ROUND(SUMIF('Line Items'!$A$2:$A$238,"<="&237,'Line Items'!$L$2:$L$238),2) -> 22935.05 | K12: =ROUND(J12-I12,2) -> 0
A15: Quantity: exact on all eight checkpoints (Diff 0). CGST: exact on all eight checkpoints (Diff 0.00).
A16: Taxable Value drifts by at most 0.04 across the whole invoice. That is the seller's half-paisa rounding accumulating, not a transcription gap - the CGST column is derived from the same taxable figures and it lands exactly, which it could not do if a row had been misread.
A17: Because Rate = M.R.P / 1.18 and Amount = M.R.P x Qty / 1.18 throughout, an error in any single M.R.P or Qty would break the quantity or CGST checkpoint for that page. None break.

Sheet HSN Summary
A1: Summary by HSN code (all lines taxed at 18%: CGST 9% + SGST 9%)
A3: HSN Code | B3: Lines | C3: Qty | D3: Taxable Value | E3: CGST | F3: SGST | G3: Total incl. GST
A4: 40169320 | B4: =COUNTIF('Line Items'!$D$2:$D$238,$A4) -> 3 | C4: =SUMIF('Line Items'!$D$2:$D$238,$A4,'Line Items'!$F$2:$F$238) -> 75 | D4: =ROUND(SUMIF('Line Items'!$D$2:$D$238,$A4,'Line Items'!$J$2:$J$238),2) -> 850.85 | E4: =ROUND(SUMIF('Line Items'!$D$2:$D$238,$A4,'Line Items'!$L$2:$L$238),2) -> 76.58 | F4: =E4 -> 76.58 | G4: =D4+E4+F4 -> 1004.01
A5: 40169330 | B5: =COUNTIF('Line Items'!$D$2:$D$238,$A5) -> 6 | C5: =SUMIF('Line Items'!$D$2:$D$238,$A5,'Line Items'!$F$2:$F$238) -> 64 | D5: =ROUND(SUMIF('Line Items'!$D$2:$D$238,$A5,'Line Items'!$J$2:$J$238),2) -> 1450.84 | E5: =ROUND(SUMIF('Line Items'!$D$2:$D$238,$A5,'Line Items'!$L$2:$L$238),2) -> 130.57 | F5: =E5 -> 130.57 | G5: =D5+E5+F5 -> 1711.98
A6: 40169390 | B6: =COUNTIF('Line Items'!$D$2:$D$238,$A6) -> 1 | C6: =SUMIF('Line Items'!$D$2:$D$238,$A6,'Line Items'!$F$2:$F$238) -> 4 | D6: =ROUND(SUMIF('Line Items'!$D$2:$D$238,$A6,'Line Items'!$J$2:$J$238),2) -> 111.19 | E6: =ROUND(SUMIF('Line Items'!$D$2:$D$238,$A6,'Line Items'!$L$2:$L$238),2) -> 10.01 | F6: =E6 -> 10.01 | G6: =D6+E6+F6 -> 131.21
A7: 40169950 | B7: =COUNTIF('Line Items'!$D$2:$D$238,$A7) -> 1 | C7: =SUMIF('Line Items'!$D$2:$D$238,$A7,'Line Items'!$F$2:$F$238) -> 10 | D7: =ROUND(SUMIF('Line Items'!$D$2:$D$238,$A7,'Line Items'!$J$2:$J$238),2) -> 542.37 | E7: =ROUND(SUMIF('Line Items'!$D$2:$D$238,$A7,'Line Items'!$L$2:$L$238),2) -> 48.81 | F7: =E7 -> 48.81 | G7: =D7+E7+F7 -> 639.99
A8: 40169990 | B8: =COUNTIF('Line Items'!$D$2:$D$238,$A8) -> 10 | C8: =SUMIF('Line Items'!$D$2:$D$238,$A8,'Line Items'!$F$2:$F$238) -> 304 | D8: =ROUND(SUMIF('Line Items'!$D$2:$D$238,$A8,'Line Items'!$J$2:$J$238),2) -> 4968.13 | E8: =ROUND(SUMIF('Line Items'!$D$2:$D$238,$A8,'Line Items'!$L$2:$L$238),2) -> 447.12 | F8: =E8 -> 447.12 | G8: =D8+E8+F8 -> 5862.37
A9: 73181500 | B9: =COUNTIF('Line Items'!$D$2:$D$238,$A9) -> 5 | C9: =SUMIF('Line Items'!$D$2:$D$238,$A9,'Line Items'!$F$2:$F$238) -> 95 | D9: =ROUND(SUMIF('Line Items'!$D$2:$D$238,$A9,'Line Items'!$J$2:$J$238),2) -> 976.27 | E9: =ROUND(SUMIF('Line Items'!$D$2:$D$238,$A9,'Line Items'!$L$2:$L$238),2) -> 87.85 | F9: =E9 -> 87.85 | G9: =D9+E9+F9 -> 1151.97
A10: 73181600 | B10: =COUNTIF('Line Items'!$D$2:$D$238,$A10) -> 5 | C10: =SUMIF('Line Items'!$D$2:$D$238,$A10,'Line Items'!$F$2:$F$238) -> 100 | D10: =ROUND(SUMIF('Line Items'!$D$2:$D$238,$A10,'Line Items'!$J$2:$J$238),2) -> 3491.52 | E10: =ROUND(SUMIF('Line Items'!$D$2:$D$238,$A10,'Line Items'!$L$2:$L$238),2) -> 314.24 | F10: =E10 -> 314.24 | G10: =D10+E10+F10 -> 4120
A11: 73181900 | B11: =COUNTIF('Line Items'!$D$2:$D$238,$A11) -> 2 | C11: =SUMIF('Line Items'!$D$2:$D$238,$A11,'Line Items'!$F$2:$F$238) -> 30 | D11: =ROUND(SUMIF('Line Items'!$D$2:$D$238,$A11,'Line Items'!$J$2:$J$238),2) -> 366.1 | E11: =ROUND(SUMIF('Line Items'!$D$2:$D$238,$A11,'Line Items'!$L$2:$L$238),2) -> 32.95 | F11: =E11 -> 32.95 | G11: =D11+E11+F11 -> 432
A12: 73202000 | B12: =COUNTIF('Line Items'!$D$2:$D$238,$A12) -> 2 | C12: =SUMIF('Line Items'!$D$2:$D$238,$A12,'Line Items'!$F$2:$F$238) -> 24 | D12: =ROUND(SUMIF('Line Items'!$D$2:$D$238,$A12,'Line Items'!$J$2:$J$238),2) -> 447.46 | E12: =ROUND(SUMIF('Line Items'!$D$2:$D$238,$A12,'Line Items'!$L$2:$L$238),2) -> 40.27 | F12: =E12 -> 40.27 | G12: =D12+E12+F12 -> 528
A13: 76161000 | B13: =COUNTIF('Line Items'!$D$2:$D$238,$A13) -> 1 | C13: =SUMIF('Line Items'!$D$2:$D$238,$A13,'Line Items'!$F$2:$F$238) -> 20 | D13: =ROUND(SUMIF('Line Items'!$D$2:$D$238,$A13,'Line Items'!$J$2:$J$238),2) -> 1220.34 | E13: =ROUND(SUMIF('Line Items'!$D$2:$D$238,$A13,'Line Items'!$L$2:$L$238),2) -> 109.83 | F13: =E13 -> 109.83 | G13: =D13+E13+F13 -> 1440
A14: 83100090 | B14: =COUNTIF('Line Items'!$D$2:$D$238,$A14) -> 2 | C14: =SUMIF('Line Items'!$D$2:$D$238,$A14,'Line Items'!$F$2:$F$238) -> 40 | D14: =ROUND(SUMIF('Line Items'!$D$2:$D$238,$A14,'Line Items'!$J$2:$J$238),2) -> 1694.92 | E14: =ROUND(SUMIF('Line Items'!$D$2:$D$238,$A14,'Line Items'!$L$2:$L$238),2) -> 152.55 | F14: =E14 -> 152.55 | G14: =D14+E14+F14 -> 2000.02
A15: 84099111 | B15: =COUNTIF('Line Items'!$D$2:$D$238,$A15) -> 1 | C15: =SUMIF('Line Items'!$D$2:$D$238,$A15,'Line Items'!$F$2:$F$238) -> 1 | D15: =ROUND(SUMIF('Line Items'!$D$2:$D$238,$A15,'Line Items'!$J$2:$J$238),2) -> 280.68 | E15: =ROUND(SUMIF('Line Items'!$D$2:$D$238,$A15,'Line Items'!$L$2:$L$238),2) -> 25.26 | F15: =E15 -> 25.26 | G15: =D15+E15+F15 -> 331.2
... A33: 90299000 | B33: =COUNTIF('Line Items'!$D$2:$D$238,$A33) -> 2 | C33: =SUMIF('Line Items'!$D$2:$D$238,$A33,'Line Items'!$F$2:$F$238) -> 4 | D33: =ROUND(SUMIF('Line Items'!$D$2:$D$238,$A33,'Line Items'!$J$2:$J$238),2) -> 1837.29 | E33: =ROUND(SUMIF('Line Items'!$D$2:$D$238,$A33,'Line Items'!$L$2:$L$238),2) -> 165.35 | F33: =E33 -> 165.35 | G33: =D33+E33+F33 -> 2167.99
A34: TOTAL | B34: =SUM(B4:B33) -> 237 | C34: =SUM(C4:C33) -> 2530 | D34: =SUM(D4:D33) -> 254833.86 | E34: =SUM(E4:E33) -> 22935.05 | F34: =SUM(F4:F33) -> 22935.05 | G34: =SUM(G4:G33) -> 300703.96
A36: Totals here must agree with the Invoice Summary sheet: 2,530 units and 254,833.90 taxable.

Sheet Invoice Summary
A1: TAX INVOICE
A3: Seller | B3: KOKILA ENTERPRISES
A4: Seller Address | B4: Aswaraopate Road, Jangareddygudem, West Godavari Dist, Andhra Pradesh - 534447
A5: Seller Phone | B5: 9440248515
A6: Seller Email | B6: bhasi.chinny@gmail.c... (truncated on invoice)
A7: Seller GSTIN | B7: 37ARTPR0091C1ZK
A8: Tax Payable on Reverse Charge | B8: (Yes/No field left blank)
A10: Invoice No. | B10: 9857
A11: Invoice Date | B11: 27-02-2026
A12: Sale Type | B12: CREDIT
A13: Copy type | B13: ORIGINAL / DUPLICATE / TRIPLICATE / EXTRA COPY (none ticked)
A14: Transport / Vehicle No / No of Ctns | B14: (all blank on invoice)
A15: Handwritten reference | B15: 129 (circled, top right of page 1)
... A25: Terms | B25: Goods once sold cannot be taken back or exchanged.
A27: TOTALS
A28: Description | C28: Printed on Invoice | D28: Recalculated
A29: Total Quantity | C29: 2530 | D29: ='Line Items'!F239 -> 2530
A30: Total Amount (pre-discount, incl. tax) | C30: 318542.37 | D30: ='Line Items'!H239 -> 318542.4
A31: Discount | C31: 0.2 | D31: n/a
A32: Taxable Amount | C32: 254833.9 | D32: ='Line Items'!J239 -> 254833.86
A33: Add CGST @ 9% | C33: 22935.05 | D33: ='Line Items'!L239 -> 22935.05
A34: Add SGST @ 9% | C34: 22935.05 | D34: ='Line Items'!N239 -> 22935.05
A35: PF | C35: 0 | D35: n/a
A36: NET AMOUNT | C36: 300704 | D36: ='Line Items'!O239 -> 300703.96
A38: Amount in words | B38: Rupees THREE LAKH SEVEN HUNDRED AND FOUR ONLY
A40: Blue = figure printed on the scanned invoice. Black = recalculated from the Line Items sheet.
A41: Pricing logic across all 237 lines: Rate = M.R.P / 1.18, Amount = Rate x Qty, Taxable Value = Amount x 80% (a flat 20% discount), then CGST and SGST at 9% each on the taxable value. The M.R.P column on the invoice is displayed rounded to whole rupees, so column P of Line Items shows the true M.R.P.
A42: 254,833.90 + 22,935.05 + 22,935.05 = 300,704.00 exactly - no rounding adjustment was needed on this invoice. The Recalculated column reads 300,703.96 because summing the 237 individually-rounded taxable values lands 0.04 below the seller total; the tax figures themselves match to the paisa.
A43: Verification: the invoice prints a running Closing Balance on each of its eight pages. Quantity and CGST reconcile exactly at all eight checkpoints; Taxable Value is within 0.04 across the entire document. See the Page Balances sheet.
