Workbook

Sheet Line Items
A1: Sn | B1: Brand Group | C1: Item Code | D1: Description | E1: HSN | F1: M.R.P | G1: Rate | H1: Qty | I1: Unit | J1: Disc % | K1: Taxable Amount | L1: CGST % | M1: CGST Value | N1: SGST % | O1: SGST Value | P1: Line Total | Q1: Cost per unit (excl. GST) | R1: Gross (MRP x Qty) | S1: Check Taxable (Rate x Qty / 1.18) | T1: Diff | U1: Page | V1: Verification
A2: 1 | B2: NV | C2: GAF144 | D2: ACCESS 125 NEW AIR FILTER | E2: 40169330 | F2: 160 | G2: 91.2 | H2: 4 | I2: PC | J2: 0.43 | K2: 309.15 | L2: 0.09 | M2: 27.82 | N2: 0.09 | O2: 27.82 | P2: =K2+M2+O2 -> 364.79 | Q2: =ROUND(K2/H2,2) -> 77.29 | R2: =F2*H2 -> 640 | S2: =ROUND(G2*H2/1.18,2) -> 309.15 | T2: =ROUND(S2-K2,2) -> 0 | U2: 1 | V2: Confirmed vs image
A3: 2 | B3: NV | C3: NAJ001 | D3: SPLENDOR AIR FILTER | E3: 40169330 | F3: 90 | G3: 51.3 | H3: 4 | J3: 0.43 | K3: 173.9 | L3: 0.09 | M3: 15.65 | N3: 0.09 | O3: 15.65 | P3: =K3+M3+O3 -> 205.2 | Q3: =ROUND(K3/H3,2) -> 43.48 | R3: =F3*H3 -> 360 | S3: =ROUND(G3*H3/1.18,2) -> 173.9 | T3: =ROUND(S3-K3,2) -> 0 | U3: 1 | V3: Confirmed vs image - CODE UNCLEAR, see note
A4: 3 | B4: NV | C4: NAN122 | D4: FOOREST ROAD XL-100 | E4: 40169330 | F4: 665 | G4: 379.05 | H4: 2 | I4: PC | J4: 0.43 | K4: 642.46 | L4: 0.09 | M4: 57.82 | N4: 0.09 | O4: 57.82 | P4: =K4+M4+O4 -> 758.1 | Q4: =ROUND(K4/H4,2) -> 321.23 | R4: =F4*H4 -> 1330 | S4: =ROUND(G4*H4/1.18,2) -> 642.46 | T4: =ROUND(S4-K4,2) -> 0 | U4: 1 | V4: Confirmed vs image
A5: 4 | B5: NV | C5: NAN132 | D5: FOOREST ROAD XL SUPER HD | E5: 40169330 | F5: 335 | G5: 190.95 | H5: 2 | I5: PC | J5: 0.43 | K5: 323.64 | L5: 0.09 | M5: 29.13 | N5: 0.09 | O5: 29.13 | P5: =K5+M5+O5 -> 381.9 | Q5: =ROUND(K5/H5,2) -> 161.82 | R5: =F5*H5 -> 670 | S5: =ROUND(G5*H5/1.18,2) -> 323.64 | T5: =ROUND(S5-K5,2) -> 0 | U5: 1 | V5: Confirmed vs image
A6: 5 | B6: NV | C6: NAN286 | D6: XL SILENCER BEND PIPE XL-SUPER 2004 | E6: 40169330 | F6: 320 | G6: 182.4 | H6: 5 | I6: PC | J6: 0.43 | K6: 772.88 | L6: 0.09 | M6: 69.56 | N6: 0.09 | O6: 69.56 | P6: =K6+M6+O6 -> 912 | Q6: =ROUND(K6/H6,2) -> 154.58 | R6: =F6*H6 -> 1600 | S6: =ROUND(G6*H6/1.18,2) -> 772.88 | T6: =ROUND(S6-K6,2) -> 0 | U6: 1 | V6: Confirmed vs image
A7: 6 | B7: NV | C7: NAN341 | D7: MUDGUARD PATTI TVS SUPER XL M.GREEN | E7: 40169330 | F7: 105 | G7: 59.85 | H7: 10 | I7: PC | J7: 0.43 | K7: 507.2 | L7: 0.09 | M7: 45.65 | N7: 0.09 | O7: 45.65 | P7: =K7+M7+O7 -> 598.5 | Q7: =ROUND(K7/H7,2) -> 50.72 | R7: =F7*H7 -> 1050 | S7: =ROUND(G7*H7/1.18,2) -> 507.2 | T7: =ROUND(S7-K7,2) -> 0 | U7: 1 | V7: Confirmed vs image
A8: 7 | B8: NV | C8: NAN344 | D8: XL SILENCER BEND PIPE XL SUPER N19 5 | E8: 40169330 | F8: 360 | G8: 205.2 | H8: 3 | I8: PC | J8: 0.43 | K8: 521.69 | L8: 0.09 | M8: 46.95 | N8: 0.09 | O8: 46.95 | P8: =K8+M8+O8 -> 615.59 | Q8: =ROUND(K8/H8,2) -> 173.9 | R8: =F8*H8 -> 1080 | S8: =ROUND(G8*H8/1.18,2) -> 521.69 | T8: =ROUND(S8-K8,2) -> 0 | U8: 1 | V8: Confirmed vs image
A9: 8 | B9: NV | C9: NAQ127 | D9: AIR FOAM HONDA ACTIVA | E9: 40169330 | F9: 16 | G9: 9.12 | H9: 10 | I9: PC | J9: 0.43 | K9: 77.29 | L9: 0.09 | M9: 6.95 | N9: 0.09 | O9: 6.95 | P9: =K9+M9+O9 -> 91.19 | Q9: =ROUND(K9/H9,2) -> 7.73 | R9: =F9*H9 -> 160 | S9: =ROUND(G9*H9/1.18,2) -> 77.29 | T9: =ROUND(S9-K9,2) -> 0 | U9: 1 | V9: Confirmed vs image
A10: 9 | B10: NV | C10: NAQ164 | D10: ACTIVA 110 AIR FILER NV | E10: 40169330 | F10: 110 | G10: 62.7 | H10: 5 | I10: PC | J10: 0.43 | K10: 265.68 | L10: 0.09 | M10: 23.91 | N10: 0.09 | O10: 23.91 | P10: =K10+M10+O10 -> 313.5 | Q10: =ROUND(K10/H10,2) -> 53.14 | R10: =F10*H10 -> 550 | S10: =ROUND(G10*H10/1.18,2) -> 265.68 | T10: =ROUND(S10-K10,2) -> 0 | U10: 1 | V10: Confirmed vs image
A11: 10 | B11: NV | C11: NAQ229 | D11: AIR FILER UNICORN | E11: 40169330 | F11: 70 | G11: 39.9 | H11: 5 | I11: PC | J11: 0.43 | K11: 169.07 | L11: 0.09 | M11: 15.21 | N11: 0.09 | O11: 15.21 | P11: =K11+M11+O11 -> 199.49 | Q11: =ROUND(K11/H11,2) -> 33.81 | R11: =F11*H11 -> 350 | S11: =ROUND(G11*H11/1.18,2) -> 169.07 | T11: =ROUND(S11-K11,2) -> 0 | U11: 1 | V11: Confirmed vs image
A12: 11 | B12: NV | C12: NAQ232 | D12: AIR FILTER SHINE | E12: 40169330 | F12: 70 | G12: 39.9 | H12: 5 | I12: PC | J12: 0.43 | K12: 169.07 | L12: 0.09 | M12: 15.21 | N12: 0.09 | O12: 15.21 | P12: =K12+M12+O12 -> 199.49 | Q12: =ROUND(K12/H12,2) -> 33.81 | R12: =F12*H12 -> 350 | S12: =ROUND(G12*H12/1.18,2) -> 169.07 | T12: =ROUND(S12-K12,2) -> 0 | U12: 1 | V12: Confirmed vs image
A13: 12 | B13: NV | C13: NAQ484 | D13: 3G AIR FILTER NV | E13: 40169330 | F13: 120 | G13: 68.4 | H13: 6 | I13: PC | J13: 0.43 | K13: 347.8 | L13: 0.09 | M13: 31.3 | N13: 0.09 | O13: 31.3 | P13: =K13+M13+O13 -> 410.4 | Q13: =ROUND(K13/H13,2) -> 57.97 | R13: =F13*H13 -> 720 | S13: =ROUND(G13*H13/1.18,2) -> 347.8 | T13: =ROUND(S13-K13,2) -> 0 | U13: 1 | V13: Confirmed vs image
A14: 13 | B14: NV | C14: NAQ530 | D14: SILENCER PATRA 3G | E14: 40169330 | F14: 30 | G14: 17.1 | H14: 5 | I14: PC | J14: 0.43 | K14: 72.46 | L14: 0.09 | M14: 6.52 | N14: 0.09 | O14: 6.52 | P14: =K14+M14+O14 -> 85.5 | Q14: =ROUND(K14/H14,2) -> 14.49 | R14: =F14*H14 -> 150 | S14: =ROUND(G14*H14/1.18,2) -> 72.46 | T14: =ROUND(S14-K14,2) -> 0 | U14: 1 | V14: Confirmed vs image
A15: 14 | B15: NV | C15: NAQ740 | D15: SILENCER BEND PIPE ACTIVA 3G | E15: 40169330 | F15: 259 | G15: 147.63 | H15: 3 | I15: PC | J15: 0.43 | K15: 375.33 | L15: 0.09 | M15: 33.78 | N15: 0.09 | O15: 33.78 | P15: =K15+M15+O15 -> 442.89 | Q15: =ROUND(K15/H15,2) -> 125.11 | R15: =F15*H15 -> 777 | S15: =ROUND(G15*H15/1.18,2) -> 375.33 | T15: =ROUND(S15-K15,2) -> 0 | U15: 1 | V15: Confirmed vs image
... A97: 96 | B97: CAMP | C97: CA15-SBP-1 | D97: BEND PIPE GLM | E97: 87141090 | F97: 250 | G97: 137.5 | H97: 3 | I97: PC | J97: 0.45 | K97: 349.58 | L97: 0.09 | M97: 31.46 | N97: 0.09 | O97: 31.46 | P97: =K97+M97+O97 -> 412.5 | Q97: =ROUND(K97/H97,2) -> 116.53 | R97: =F97*H97 -> 750 | S97: =ROUND(G97*H97/1.18,2) -> 349.58 | T97: =ROUND(S97-K97,2) -> 0 | U97: 4 | V97: Confirmed vs image
A98: 97 | B98: MUD | C98: MUD-01 | D98: ACTIVA F MUDCAR WHITE 3G | E98: 8714 | F98: 780 | G98: 780 | H98: 3 | I98: PC | K98: 1983.05 | L98: 0.09 | M98: 178.47 | N98: 0.09 | O98: 178.47 | P98: =K98+M98+O98 -> 2339.99 | Q98: =ROUND(K98/H98,2) -> 661.02 | R98: =F98*H98 -> 2340 | S98: =ROUND(G98*H98/1.18,2) -> 1983.05 | T98: =ROUND(S98-K98,2) -> 0 | U98: 4 | V98: Confirmed vs image
A99: 98 | B99: MUD | C99: MUD-01A | D99: ACTIVA F MUDCAR 6G WHITE | E99: 8714 | F99: 780 | G99: 780 | H99: 2 | I99: PC | K99: 1322.03 | L99: 0.09 | M99: 118.98 | N99: 0.09 | O99: 118.98 | P99: =K99+M99+O99 -> 1559.99 | Q99: =ROUND(K99/H99,2) -> 661.02 | R99: =F99*H99 -> 1560 | S99: =ROUND(G99*H99/1.18,2) -> 1322.03 | T99: =ROUND(S99-K99,2) -> 0 | U99: 4 | V99: Confirmed vs image
A100: 99 | B100: MUD | C100: MUD-01A RE | D100: ACTIVA F MUDCAR 6G BALCK | E100: 8714 | F100: 780 | G100: 780 | H100: 2 | I100: PC | K100: 1322.03 | L100: 0.09 | M100: 118.98 | N100: 0.09 | O100: 118.98 | P100: =K100+M100+O100 -> 1559.99 | Q100: =ROUND(K100/H100,2) -> 661.02 | R100: =F100*H100 -> 1560 | S100: =ROUND(G100*H100/1.18,2) -> 1322.03 | T100: =ROUND(S100-K100,2) -> 0 | U100: 4 | V100: Confirmed vs image
A101: 100 | B101: MUD | C101: MUD-01AA | D101: ACTIVA F MUDCAR GREY 3G | E101: 8714 | F101: 780 | G101: 780 | H101: 2 | I101: PC | K101: 1322.03 | L101: 0.09 | M101: 118.98 | N101: 0.09 | O101: 118.98 | P101: =K101+M101+O101 -> 1559.99 | Q101: =ROUND(K101/H101,2) -> 661.02 | R101: =F101*H101 -> 1560 | S101: =ROUND(G101*H101/1.18,2) -> 1322.03 | T101: =ROUND(S101-K101,2) -> 0 | U101: 4 | V101: Confirmed vs image
A102: 101 | B102: MUD | C102: MUD-03BL | D102: ACTIVA F MUDCAR 3G BLUE | E102: 8714 | F102: 780 | G102: 780 | H102: 1 | I102: PC | K102: 661.02 | L102: 0.09 | M102: 59.49 | N102: 0.09 | O102: 59.49 | P102: =K102+M102+O102 -> 780 | Q102: =ROUND(K102/H102,2) -> 661.02 | R102: =F102*H102 -> 780 | S102: =ROUND(G102*H102/1.18,2) -> 661.02 | T102: =ROUND(S102-K102,2) -> 0 | U102: 4 | V102: Confirmed vs image
A103: 102 | B103: BHARATH IND | C103: PL-1519ABS | D103: IND SET PSN PRO N/M BS6 UNI | E103: 85122010 | F103: 286 | G103: 157.3 | H103: 10 | I103: SET | J103: 0.45 | K103: 1333.05 | L103: 0.09 | M103: 119.97 | N103: 0.09 | O103: 119.97 | P103: =K103+M103+O103 -> 1572.99 | Q103: =ROUND(K103/H103,2) -> 133.31 | R103: =F103*H103 -> 2860 | S103: =ROUND(G103*H103/1.18,2) -> 1333.05 | T103: =ROUND(S103-K103,2) -> 0 | U103: 4 | V103: Confirmed vs image
A104: 103 | B104: BHARATH IND | C104: PL-1526QXP | D104: PLTN IND SET RED | E104: 85122010 | F104: 250 | G104: 137.5 | H104: 10 | I104: SET | J104: 0.45 | K104: 1165.25 | L104: 0.09 | M104: 104.87 | N104: 0.09 | O104: 104.87 | P104: =K104+M104+O104 -> 1374.99 | Q104: =ROUND(K104/H104,2) -> 116.53 | R104: =F104*H104 -> 2500 | S104: =ROUND(G104*H104/1.18,2) -> 1165.25 | T104: =ROUND(S104-K104,2) -> 0 | U104: 4 | V104: Confirmed vs image
A105: 104 | B105: BHARATH IND | C105: PL-M03L | D105: MIRROR SPL PLUS LHS | E105: 85122010 | F105: 135 | G105: 74.25 | H105: 8 | I105: PC | J105: 0.45 | K105: 503.39 | L105: 0.09 | M105: 45.3 | N105: 0.09 | O105: 45.3 | P105: =K105+M105+O105 -> 593.99 | Q105: =ROUND(K105/H105,2) -> 62.92 | R105: =F105*H105 -> 1080 | S105: =ROUND(G105*H105/1.18,2) -> 503.39 | T105: =ROUND(S105-K105,2) -> 0 | U105: 4 | V105: Confirmed vs image
A106: 105 | B106: BHARATH IND | C106: PL-M03R | D106: MIRROR SPL PLUS RHS | E106: 85122010 | F106: 135 | G106: 74.25 | H106: 8 | I106: PC | J106: 0.45 | K106: 503.39 | L106: 0.09 | M106: 45.3 | N106: 0.09 | O106: 45.3 | P106: =K106+M106+O106 -> 593.99 | Q106: =ROUND(K106/H106,2) -> 62.92 | R106: =F106*H106 -> 1080 | S106: =ROUND(G106*H106/1.18,2) -> 503.39 | T106: =ROUND(S106-K106,2) -> 0 | U106: 4 | V106: Confirmed vs image
A107: TOTAL | D107: 105 line items | H107: =SUM(H2:H106) -> 679 | K107: =SUM(K2:K106) -> 57468.52 | M107: =SUM(M2:M106) -> 5171.91 | O107: =SUM(O2:O106) -> 5171.91 | P107: =SUM(P2:P106) -> 67812.34 | R107: =SUM(R2:R106) -> 106552 | S107: =SUM(S2:S106) -> 57468.52 | T107: =SUM(T2:T106) -> 0
A109: PRICING RULE, holds on all 105 lines: Taxable Amount = ROUND(Rate x Qty / 1.18, 2). Rate is M.R.P less the brand-group discount in column J. Column S recomputes it, column T is the difference - 0.00 on every row.
A110: INVENTORY: use the orange 'Cost per unit' column for stock valuation, not Rate. Rate is per unit before the GST split; the cost you bear is the line's taxable amount divided by quantity.
A111: VERIFICATION: all 105 rows have been confirmed field-by-field against legible images of all four pages. Corrections applied: Sn 53 unit SET -> PC; Sn 68 description SHINE HALF SET -> SHINE HALE SET (the seller's own typo); Sn 94 and 95 description SM -> SVM. In addition the invoice's 18 brand-group checkpoints (Gross and Net for each of 9 groups) all reconcile exactly, quantity 679 matches, and every line satisfies Taxable = Rate x Qty / 1.18.
A112: ONE UNRESOLVED CHARACTER: Sn 2 item code. The scan renders it as NAQ001, but every one of the 105 codes on this invoice sorts in ascending order within its brand group, and NAQ001 would break that (it would fall after NAN122). NAJ001 fits the sort. The file keeps NAJ001 - please confirm the third character against the paper original.
A113: Sn 8 item code is partly obscured by a scan mark and was read as NAQ127 from the surrounding code sequence. Sn 97-101 (MUD) carry no printed discount - Rate equals M.R.P - and a 4-digit HSN of 8714.

Sheet Group Reconciliation
A1: Brand-group reconciliation - 18 checkpoints
A2: The invoice prints Gross and Net for each brand group. Gross constrains M.R.P and Qty; Net constrains Rate and Qty. Two independent checks per group.
A4: Brand Group | B4: Rows | C4: Gross printed | D4: Gross calc | E4: Diff | F4: Net printed | G4: Net calc | H4: Diff | I4: Row-level confidence
A5: NV | B5: 18 | C5: 12317 | D5: =ROUND(SUMIF('Line Items'!$B$2:$B$106,$A5,'Line Items'!$R$2:$R$106),2) -> 12317 | E5: =ROUND(D5-C5,2) -> 0 | F5: 5949.74 | G5: =ROUND(SUMIF('Line Items'!$B$2:$B$106,$A5,'Line Items'!$K$2:$K$106),2) -> 5949.74 | H5: =ROUND(G5-F5,2) -> 0 | I5: All 18 rows confirmed vs image
A6: SILVERUP | B6: 2 | C6: 1640 | D6: =ROUND(SUMIF('Line Items'!$B$2:$B$106,$A6,'Line Items'!$R$2:$R$106),2) -> 1640 | E6: =ROUND(D6-C6,2) -> 0 | F6: 861.7 | G6: =ROUND(SUMIF('Line Items'!$B$2:$B$106,$A6,'Line Items'!$K$2:$K$106),2) -> 861.7 | H6: =ROUND(G6-F6,2) -> 0 | I6: All 2 rows confirmed vs image
A7: ROLAN | B7: 1 | C7: 1600 | D7: =ROUND(SUMIF('Line Items'!$B$2:$B$106,$A7,'Line Items'!$R$2:$R$106),2) -> 1600 | E7: =ROUND(D7-C7,2) -> 0 | F7: 976.27 | G7: =ROUND(SUMIF('Line Items'!$B$2:$B$106,$A7,'Line Items'!$K$2:$K$106),2) -> 976.27 | H7: =ROUND(G7-F7,2) -> 0 | I7: All 1 rows confirmed vs image
A8: REMSONS | B8: 30 | C8: 23930 | D8: =ROUND(SUMIF('Line Items'!$B$2:$B$106,$A8,'Line Items'!$R$2:$R$106),2) -> 23930 | E8: =ROUND(D8-C8,2) -> 0 | F8: 12167.78 | G8: =ROUND(SUMIF('Line Items'!$B$2:$B$106,$A8,'Line Items'!$K$2:$K$106),2) -> 12167.78 | H8: =ROUND(G8-F8,2) -> 0 | I8: All 30 rows confirmed vs image
A9: SGI GASKETS | B9: 27 | C9: 20331 | D9: =ROUND(SUMIF('Line Items'!$B$2:$B$106,$A9,'Line Items'!$R$2:$R$106),2) -> 20331 | E9: =ROUND(D9-C9,2) -> 0 | F9: 9993.19 | G9: =ROUND(SUMIF('Line Items'!$B$2:$B$106,$A9,'Line Items'!$K$2:$K$106),2) -> 9993.19 | H9: =ROUND(G9-F9,2) -> 0 | I9: All 27 rows confirmed vs image
A10: LUMAX IND | B10: 17 | C10: 30664 | D10: =ROUND(SUMIF('Line Items'!$B$2:$B$106,$A10,'Line Items'!$R$2:$R$106),2) -> 30664 | E10: =ROUND(D10-C10,2) -> 0 | F10: 17055.02 | G10: =ROUND(SUMIF('Line Items'!$B$2:$B$106,$A10,'Line Items'!$K$2:$K$106),2) -> 17055.02 | H10: =ROUND(G10-F10,2) -> 0 | I10: All 17 rows confirmed vs image
A11: CAMP | B11: 1 | C11: 750 | D11: =ROUND(SUMIF('Line Items'!$B$2:$B$106,$A11,'Line Items'!$R$2:$R$106),2) -> 750 | E11: =ROUND(D11-C11,2) -> 0 | F11: 349.58 | G11: =ROUND(SUMIF('Line Items'!$B$2:$B$106,$A11,'Line Items'!$K$2:$K$106),2) -> 349.58 | H11: =ROUND(G11-F11,2) -> 0 | I11: All 1 rows confirmed vs image
A12: MUD | B12: 5 | C12: 7800 | D12: =ROUND(SUMIF('Line Items'!$B$2:$B$106,$A12,'Line Items'!$R$2:$R$106),2) -> 7800 | E12: =ROUND(D12-C12,2) -> 0 | F12: 6610.16 | G12: =ROUND(SUMIF('Line Items'!$B$2:$B$106,$A12,'Line Items'!$K$2:$K$106),2) -> 6610.16 | H12: =ROUND(G12-F12,2) -> 0 | I12: All 5 rows confirmed vs image
A13: BHARATH IND | B13: 4 | C13: 7520 | D13: =ROUND(SUMIF('Line Items'!$B$2:$B$106,$A13,'Line Items'!$R$2:$R$106),2) -> 7520 | E13: =ROUND(D13-C13,2) -> 0 | F13: 3505.08 | G13: =ROUND(SUMIF('Line Items'!$B$2:$B$106,$A13,'Line Items'!$K$2:$K$106),2) -> 3505.08 | H13: =ROUND(G13-F13,2) -> 0 | I13: All 4 rows confirmed vs image
A14: TOTAL | B14: =SUM(B5:B13) -> 105 | C14: =SUM(C5:C13) -> 106552 | D14: =SUM(D5:D13) -> 106552 | E14: =SUM(E5:E13) -> 0 | F14: =SUM(F5:F13) -> 57468.52 | G14: =SUM(G5:G13) -> 57468.52 | H14: =SUM(H5:H13) -> 0

Sheet Invoice Summary
A1: TAX INVOICE - CREDIT
A3: Seller | B3: KUMAR AUTO STORES
A4: Seller Address | B4: D.NO.4-18/1 Garagaparru Road, Bhimavaram - 534 202
A5: Seller Phone | B5: 9397111911
A6: Seller GSTIN | B6: 37AITPG4383P1ZB
A7: Invoice No. | B7: 5560GS
A8: Invoice Date | B8: 6/03/2026
A9: Buyer Code | B9: 02170
A10: Buyer | B10: SRI SRI SATYA SAI AUTMOBILE AGENC
A11: Buyer Address | B11: 2-12-27/1, Railway Station Road, Tadepalligudem - 534101
A12: Buyer Phone | B12: CEL-9848725117
A13: Buyer GSTIN | B13: 37CUJPG4763K1Z5
A14: Terms | B14: Subject to Bhimavaram jurisdiction. Goods once sold cannot be taken back or exchanged. E. & O.E.
... A16: Note on codes | B16: Codes are Kumar's own brand-group codes, NOT Honda part numbers. They do not join to the Kokila or Gayatri item codes.
A18: TOTALS
A19: Description | C19: Printed | D19: Recalculated
A20: Total Quantity | C20: 679 | D20: ='Line Items'!H107 -> 679
A21: Sub Total (Taxable) | C21: 57468.52 | D21: ='Line Items'!K107 -> 57468.52
A22: CGST Amount @ 9% | C22: 5172.18 | D22: =ROUND('Line Items'!K107*9%,2) -> 5172.17
A23: SGST Amount @ 9% | C23: 5172.18 | D23: =ROUND('Line Items'!K107*9%,2) -> 5172.17
A24: Rounding off | C24: 0.12 | D24: —
A25: NET AMOUNT | C25: 67813 | D25: —
A26: Total Gross (MRP x Qty) | C26: not printed | D26: ='Line Items'!R107 -> 106552
A28: Amount in words | B28: Rs SIXTY SEVEN THOUSAND EIGHT HUNDRED THIRTEEN Only
A30: The seller charges CGST and SGST at 9% each on the invoice sub-total, not per line. 57,468.52 x 9% = 5,172.17; the invoice prints 5,172.18. Summing the 105 rounded per-line figures instead gives 5,171.91. Use the printed figures for GST filing.
A31: Footer inconsistency in the original: the 'GST SALES 18%' line reads 10,344.37, while the invoice's own CGST + SGST comes to 10,344.36 and a true 18% of the sub-total is 10,344.33. Three slightly different tax figures on one page. The Net Amount of 67,813.00 is unaffected.
